Workbook
Name AcquirorLFY: #REF!
Name AcquirorLFY: #REF!
Name case: #REF!
Name circ: #REF!
Name company: Notes!$C$4
Name currency: Notes!$C$8
Name g: DCF!$C$22
Name LFY: Notes!$C$6
Name WACC: DCF!$C$21

Sheet Notes
A1: =company&" Model" -> BELLWAY P L C Model
A2: Notes
B4: Company name | C4: BELLWAY P L C
B5: Financials used | C5: Annual
B6: Date of financials | C6: 2023
B7: Forecasts | C7: Training
B8: Currency | C8: GBP
B11: Tasks
A12: 1 | B12: Forecast the financials of the company
A13: 2 | B13: Build a free cash flow forecast
A14: 3 | B14: Assume a WACC of 8%
A15: 4 | B15: Assume a long term growth rate of 1.0%
A16: 5 | B16: Perform the DCF analysis of the company and calculate the implied price per share. Number of shares =119,450 th.
A17: 6 | B17: Add a data table varying WACC and the long term growth rate by 0.5%, one variation up and one down
A18: 7 | B18: Add a scenario analysis on sales growth, using the current forecast as base case. Vary upside case by +1%, downside case by -1%

Sheet Assumptions
A1: =company&" Assumptions" -> BELLWAY P L C Assumptions
A2: ="in "&currency&" thousands" -> in GBP thousands
B4: Downside
E5: =LFY+1 -> 2024 | F5: =LFY+2 -> 2025 | G5: =LFY+3 -> 2026 | H5: =LFY+4 -> 2027 | I5: =LFY+5 -> 2028 | J5: =LFY+6 -> 2029
B6: Base case | E6: 0.02 | F6: 0.02 | G6: 0.02 | H6: 0.02 | I6: 0.02 | J6: 0.02
B7: Upside | E7: =E6+1% -> 0.03 | F7: =F6+1% -> 0.03 | G7: =G6+1% -> 0.03 | H7: =H6+1% -> 0.03 | I7: =I6+1% -> 0.03 | J7: =J6+1% -> 0.03
B8: Downside | E8: =E6-1% -> 0.01 | F8: =F6-1% -> 0.01 | G8: =G6-1% -> 0.01 | H8: =H6-1% -> 0.01 | I8: =I6-1% -> 0.01 | J8: =J6-1% -> 0.01
A10: Income statement | C10: =LFY-1 -> 2022 | D10: =LFY -> 2023 | E10: =LFY+1 -> 2024 | F10: =LFY+2 -> 2025 | G10: =LFY+3 -> 2026 | H10: =LFY+4 -> 2027 | I10: =LFY+5 -> 2028 | J10: =LFY+6 -> 2029
B11: Sales growth | D11: ='Income Statement'!D9/'Income Statement'!C9-1 -> -0.036812938 | E11: =VLOOKUP($B$4,$B$6:$J$8,MATCH(E5,$E$10:$J$10)+3,FALSE) -> 0.01 | F11: =VLOOKUP($B$4,$B$6:$J$8,MATCH(F5,$E$10:$J$10)+3,FALSE) -> 0.01 | G11: =VLOOKUP($B$4,$B$6:$J$8,MATCH(G5,$E$10:$J$10)+3,FALSE) -> 0.01 | H11: =VLOOKUP($B$4,$B$6:$J$8,MATCH(H5,$E$10:$J$10)+3,FALSE) -> 0.01 | I11: =VLOOKUP($B$4,$B$6:$J$8,MATCH(I5,$E$10:$J$10)+3,FALSE) -> 0.01 | J11: =VLOOKUP($B$4,$B$6:$J$8,MATCH(J5,$E$10:$J$10)+3,FALSE) -> 0.01
B12: Cost of goods sold/sales | C12: =-'Income Statement'!C10/'Income Statement'!C9 -> 0.87480208 | D12: =-'Income Statement'!D10/'Income Statement'!D9 -> 0.80957553 | E12: 0.84 | F12: 0.84 | G12: 0.84 | H12: 0.84 | I12: 0.84 | J12: 0.84
B13: Administration/sales | C13: =-'Income Statement'!C14/'Income Statement'!C9 -> 0.044984166 | D13: =-'Income Statement'!D14/'Income Statement'!D9 -> 0.050636999 | E13: 0.05 | F13: 0.05 | G13: 0.05 | H13: 0.05 | I13: 0.05 | J13: 0.05
B14: Other operating income £th | C14: ='Income Statement'!C15 -> 40700 | D14: ='Income Statement'!D15 -> 33700 | E14: 30000 | F14: 30000 | G14: 30000 | H14: 30000 | I14: 30000 | J14: 30000
B15: Exceptional items pre OP £th | C15: ='Income Statement'!C32 -> 0 | D15: ='Income Statement'!D32 -> 0 | E15: 0 | F15: 0 | G15: 0 | H15: 0 | I15: 0 | J15: 0
B16: Depreciation/year end PP&E | C16: =-'Income Statement'!C20/'Balance sheet'!C15 -> 0.44852941 | D16: =-'Income Statement'!D20/'Balance sheet'!D15 -> 0.4137931 | E16: 0.42 | F16: 0.42 | G16: 0.42 | H16: 0.42 | I16: 0.42 | J16: 0.42
B17: Amortisation and impairment/year end Intangibles | C17: =-'Income Statement'!C21/'Balance sheet'!C16 -> 0 | D17: =-'Income Statement'!D21/'Balance sheet'!D16 -> 0 | E17: 0 | F17: 0 | G17: 0 | H17: 0 | I17: 0 | J17: 0
B18: Interest income/end-year cash and ST inv | C18: ='Income Statement'!C25/'Balance sheet'!C9 -> 0.0042632561 | D18: ='Income Statement'!D25/'Balance sheet'!D9 -> 0.027348066 | E18: 0.03 | F18: 0.03 | G18: 0.03 | H18: 0.03 | I18: 0.03 | J18: 0.03
B19: Tax rate | C19: =-'Income Statement'!C29/'Income Statement'!C27 -> 0.20249836 | D19: =-'Income Statement'!D29/'Income Statement'!D27 -> 0.24430642 | E19: 0.25 | F19: 0.25 | G19: 0.25 | H19: 0.25 | I19: 0.25 | J19: 0.25
B20: Extraordinary items £th | C20: ='Income Statement'!C32 -> 0 | D20: ='Income Statement'!D32 -> 0 | E20: 0 | F20: 0 | G20: 0 | H20: 0 | I20: 0 | J20: 0
A22: Balance sheet
B23: Accounts receivable/sales | C23: ='Balance sheet'!C10/'Income Statement'!C9 -> 0.013430219 | D23: ='Balance sheet'!D10/'Income Statement'!D9 -> 0.010156755 | E23: 0.01 | F23: 0.01 | G23: 0.01 | H23: 0.01 | I23: 0.01 | J23: 0.01
B24: Inventories/sales | C24: ='Balance sheet'!C11/'Income Statement'!C9 -> 1.2507351 | D24: ='Balance sheet'!D11/'Income Statement'!D9 -> 1.3431574 | E24: 1.3 | F24: 1.3 | G24: 1.3 | H24: 1.3 | I24: 1.3 | J24: 1.3
B25: Other current assets/sales | C25: ='Balance sheet'!C12/'Income Statement'!C9 -> 0.018971952 | D25: ='Balance sheet'!D12/'Income Statement'!D9 -> 0.018346739 | E25: 0.018 | F25: 0.018 | G25: 0.018 | H25: 0.018 | I25: 0.018 | J25: 0.018
B26: Capex/sales | C26: ='Side calculations'!C10/'Income Statement'!C9 -> -0.0017529971 | D26: ='Side calculations'!D10/'Income Statement'!D9 -> 0 | E26: 0.01 | F26: 0.01 | G26: 0.01 | H26: 0.01 | I26: 0.01 | J26: 0.01
B27: Goodwill and intangible assets £th | C27: ='Balance sheet'!C16 -> 37400 | D27: ='Balance sheet'!D16 -> 47700 | E27: =D27 -> 47700 | F27: =E27 -> 47700 | G27: =F27 -> 47700 | H27: =G27 -> 47700 | I27: =H27 -> 47700 | J27: =I27 -> 47700
B28: Other long term assets/sales | C28: ='Balance sheet'!C17/'Income Statement'!C9 -> 0.0058244741 | D28: ='Balance sheet'!D17/'Income Statement'!D9 -> 0.0050490225 | E28: 0.005 | F28: 0.005 | G28: 0.005 | H28: 0.005 | I28: 0.005 | J28: 0.005
B30: Accounts payable/sales | C30: =-'Balance sheet'!C22/'Income Statement'!C9 -> 0.16543203 | D30: =-'Balance sheet'!D22/'Income Statement'!D9 -> 0.17014032 | E30: 0.17 | F30: 0.17 | G30: 0.17 | H30: 0.17 | I30: 0.17 | J30: 0.17
B31: Other current liabilities/sales | C31: =-'Balance sheet'!C23/'Income Statement'!C9 -> 0.10828998 | D31: =-'Balance sheet'!D23/'Income Statement'!D9 -> 0.12411202 | E31: 0.12 | F31: 0.12 | G31: 0.12 | H31: 0.12 | I31: 0.12 | J31: 0.12
B32: Other LT liabiities/sales | C32: =-'Balance sheet'!C27/'Income Statement'!C9 -> 0.026097037 | D32: =-'Balance sheet'!D27/'Income Statement'!D9 -> 0.028004462 | E32: 0.028 | F32: 0.028 | G32: 0.028 | H32: 0.028 | I32: 0.028 | J32: 0.028
B33: Provision for liabilities £th | C33: =-'Balance sheet'!C28 -> 409700 | D33: =-'Balance sheet'!D28 -> 409700 | E33: =D33 -> 409700 | F33: =E33 -> 409700 | G33: =F33 -> 409700 | H33: =G33 -> 409700 | I33: =H33 -> 409700 | J33: =I33 -> 409700
B34: Pension liabilities £th | C34: =-'Balance sheet'!C29 -> 0 | D34: =-'Balance sheet'!D29 -> 0 | E34: 0 | F34: 0 | G34: 0 | H34: 0 | I34: 0 | J34: 0
B35: Dividend payout ratio | C35: =-'Side calculations'!C17/'Income Statement'!C33 -> 0.64798021 | D35: =-'Side calculations'!D17/'Income Statement'!D33 -> 0.47041096 | E35: 0.5 | F35: 0.5 | G35: 0.5 | H35: 0.5 | I35: 0.5 | J35: 0.5
A37: Debt assumptions
B38: Long term debt repayment (borrowings) | E38: 5000 | F38: 5000 | G38: 10000 | H38: 10000 | I38: 10000 | J38: 10000
B39: Short term debt repayment | E39: 500 | F39: 500 | G39: 0 | H39: 0 | I39: 0 | J39: 0
B40: Long term debt interest rate | E40: 0.035 | F40: 0.04 | G40: 0.04 | H40: 0.04 | I40: 0.04 | J40: 0.04
B41: Short term debt interest rate | E41: 0.02 | F41: 0.025 | G41: 0.025 | H41: 0.025 | I41: 0.025 | J41: 0.025

Sheet Side calculations
A1: =company&" Side Calculations" -> BELLWAY P L C Side Calculations
A2: ="in "&currency&" thousands" -> in GBP thousands
C6: =Assumptions!C10 -> 2022 | D6: =Assumptions!D10 -> 2023 | E6: =Assumptions!E10 -> 2024 | F6: =Assumptions!F10 -> 2025 | G6: =Assumptions!G10 -> 2026 | H6: =Assumptions!H10 -> 2027 | I6: =Assumptions!I10 -> 2028 | J6: =Assumptions!J10 -> 2029
B8: PP&E
B9: Beginning balance | E9: ='Balance sheet'!D15 -> 14500 | F9: =E12 -> 34681.211 | G9: =F12 -> 49382.731 | H9: =G12 -> 60235.1 | I9: =H12 -> 68386.785 | J9: =I12 -> 74646.762
B10: Capex | C10: -6200 | D10: =D12-D11-D9 -> 0 | E10: =Assumptions!E26*'Income Statement'!E9 -> 34406.66 | F10: =Assumptions!F26*'Income Statement'!F9 -> 34750.727 | G10: =Assumptions!G26*'Income Statement'!G9 -> 35098.234 | H10: =Assumptions!H26*'Income Statement'!H9 -> 35449.216 | I10: =Assumptions!I26*'Income Statement'!I9 -> 35803.708 | J10: =Assumptions!J26*'Income Statement'!J9 -> 36161.745
B11: Depreciation | E11: =-Assumptions!E16*'Side calculations'!E12 -> -14566.109 | F11: =-Assumptions!F16*'Side calculations'!F12 -> -20740.747 | G11: =-Assumptions!G16*'Side calculations'!G12 -> -25298.742 | H11: =-Assumptions!H16*'Side calculations'!H12 -> -28722.45 | I11: =-Assumptions!I16*'Side calculations'!I12 -> -31351.64 | J11: =-Assumptions!J16*'Side calculations'!J12 -> -33425.674
B12: Ending balance | E12: =SUM(E9:E11) -> 34681.211 | F12: =SUM(F9:F11) -> 49382.731 | G12: =SUM(G9:G11) -> 60235.1 | H12: =SUM(H9:H11) -> 68386.785 | I12: =SUM(I9:I11) -> 74646.762 | J12: =SUM(J9:J11) -> 79584.937
B14: Equity
B15: Beginning balance | E15: =+D18 -> 3461600 | F15: =+E18 -> 3615114.1 | G15: =+F18 -> 3769710.6 | H15: =+G18 -> 3926355.1 | I15: =+H18 -> 4085609.9 | J15: =+I18 -> 4247871.2
B16: Net income | E16: =+'Income Statement'!E33 -> 307028.11 | F16: ='Income Statement'!F33 -> 309193.18 | G16: ='Income Statement'!G33 -> 313288.84 | H16: ='Income Statement'!H33 -> 318509.61 | I16: ='Income Statement'!I33 -> 324522.75 | J16: ='Income Statement'!J33 -> 331144.5
B17: Dividends | C17: -157200 | D17: -171700 | E17: =-Assumptions!E35*E16 -> -153514.05 | F17: =-Assumptions!F35*F16 -> -154596.59 | G17: =-Assumptions!G35*G16 -> -156644.42 | H17: =-Assumptions!H35*H16 -> -159254.8 | I17: =-Assumptions!I35*I16 -> -162261.38 | J17: =-Assumptions!J35*J16 -> -165572.25
B18: Ending balance | D18: =-'Balance sheet'!D32 -> 3461600 | E18: =SUM(E15:E17) -> 3615114.1 | F18: =SUM(F15:F17) -> 3769710.6 | G18: =SUM(G15:G17) -> 3926355.1 | H18: =SUM(H15:H17) -> 4085609.9 | I18: =SUM(I15:I17) -> 4247871.2 | J18: =SUM(J15:J17) -> 4413443.5
B20: Long term debt
B21: Beginning balance | E21: =D23 -> 141900 | F21: =+E23 -> 136900 | G21: =+F23 -> 131900 | H21: =+G23 -> 121900 | I21: =+H23 -> 111900 | J21: =+I23 -> 101900
B22: (Repayment)/increase in debt | E22: =-Assumptions!E38 -> -5000 | F22: =-Assumptions!F38 -> -5000 | G22: =-Assumptions!G38 -> -10000 | H22: =-Assumptions!H38 -> -10000 | I22: =-Assumptions!I38 -> -10000 | J22: =-Assumptions!J38 -> -10000
B23: Ending balance | D23: =-'Balance sheet'!D26 -> 141900 | E23: =SUM(E21:E22) -> 136900 | F23: =SUM(F21:F22) -> 131900 | G23: =SUM(G21:G22) -> 121900 | H23: =SUM(H21:H22) -> 111900 | I23: =SUM(I21:I22) -> 101900 | J23: =SUM(J21:J22) -> 91900
B24: Interest expense | E24: =Assumptions!E40*AVERAGE('Side calculations'!D23:E23) -> 4879 | F24: =Assumptions!F40*AVERAGE('Side calculations'!E23:F23) -> 5376 | G24: =Assumptions!G40*AVERAGE('Side calculations'!F23:G23) -> 5076 | H24: =Assumptions!H40*AVERAGE('Side calculations'!G23:H23) -> 4676 | I24: =Assumptions!I40*AVERAGE('Side calculations'!H23:I23) -> 4276 | J24: =Assumptions!J40*AVERAGE('Side calculations'!I23:J23) -> 3876
B26: Short term debt
B27: Beginning balance | E27: =D29 -> 3100 | F27: =E29 -> 2600 | G27: =F29 -> 2100 | H27: =G29 -> 2100 | I27: =H29 -> 2100 | J27: =I29 -> 2100
B28: (Repayment)/increase in debt | E28: =-Assumptions!E39 -> -500 | F28: =-Assumptions!F39 -> -500 | G28: =-Assumptions!G39 -> 0 | H28: =-Assumptions!H39 -> 0 | I28: =-Assumptions!I39 -> 0 | J28: =+Assumptions!J39 -> 0
B29: Ending balance | D29: =-'Balance sheet'!D21 -> 3100 | E29: =SUM(E27+E28) -> 2600 | F29: =SUM(F27+F28) -> 2100 | G29: =SUM(G27+G28) -> 2100 | H29: =SUM(H27+H28) -> 2100 | I29: =SUM(I27+I28) -> 2100 | J29: =SUM(J27+J28) -> 2100
B30: Interest expense | E30: =Assumptions!E41*AVERAGE('Side calculations'!D29:E29) -> 57 | F30: =Assumptions!F41*AVERAGE('Side calculations'!E29:F29) -> 58.75 | G30: =Assumptions!G41*AVERAGE('Side calculations'!F29:G29) -> 52.5 | H30: =Assumptions!H41*AVERAGE('Side calculations'!G29:H29) -> 52.5 | I30: =Assumptions!I41*AVERAGE('Side calculations'!H29:I29) -> 52.5 | J30: =Assumptions!J41*AVERAGE('Side calculations'!I29:J29) -> 52.5
B32: Working capital (for DCF) | C32: ='Balance sheet'!C10+'Balance sheet'!C11+'Balance sheet'!C12-'Balance sheet'!C22-'Balance sheet'!C23 -> 5506300 | D32: ='Balance sheet'!D10+'Balance sheet'!D11+'Balance sheet'!D12-'Balance sheet'!D22-'Balance sheet'!D23 -> 5675100 | E32: ='Balance sheet'!E10+'Balance sheet'!E11+'Balance sheet'!E12-'Balance sheet'!E22-'Balance sheet'!E23 -> 5566997.6 | F32: ='Balance sheet'!F10+'Balance sheet'!F11+'Balance sheet'!F12-'Balance sheet'!F22-'Balance sheet'!F23 -> 5622667.6 | G32: ='Balance sheet'!G10+'Balance sheet'!G11+'Balance sheet'!G12-'Balance sheet'!G22-'Balance sheet'!G23 -> 5678894.2 | H32: ='Balance sheet'!H10+'Balance sheet'!H11+'Balance sheet'!H12-'Balance sheet'!H22-'Balance sheet'!H23 -> 5735683.2 | I32: ='Balance sheet'!I10+'Balance sheet'!I11+'Balance sheet'!I12-'Balance sheet'!I22-'Balance sheet'!I23 -> 5793040 | J32: ='Balance sheet'!J10+'Balance sheet'!J11+'Balance sheet'!J12-'Balance sheet'!J22-'Balance sheet'!J23 -> 5850970.4

Sheet Income Statement
A1: =company&" Income Statement" -> BELLWAY P L C Income Statement
A2: ="in "&currency&" thousands" -> in GBP thousands
A5: Income statement
C7: =Assumptions!C10 -> 2022 | D7: =Assumptions!D10 -> 2023 | E7: =Assumptions!E10 -> 2024 | F7: =Assumptions!F10 -> 2025 | G7: =Assumptions!G10 -> 2026 | H7: =Assumptions!H10 -> 2027 | I7: =Assumptions!I10 -> 2028 | J7: =Assumptions!J10 -> 2029
B9: Sales | C9: 3536800 | D9: 3406600 | E9: =(1+Assumptions!E11)*'Income Statement'!D9 -> 3440666 | F9: =(1+Assumptions!F11)*'Income Statement'!E9 -> 3475072.7 | G9: =(1+Assumptions!G11)*'Income Statement'!F9 -> 3509823.4 | H9: =(1+Assumptions!H11)*'Income Statement'!G9 -> 3544921.6 | I9: =(1+Assumptions!I11)*'Income Statement'!H9 -> 3580370.8 | J9: =(1+Assumptions!J11)*'Income Statement'!I9 -> 3616174.5
B10: COGS excl dep'n & amort'n | C10: -3094000 | D10: =-2757900 -> -2757900 | E10: =-Assumptions!E12* 'Income Statement'!E9 -> -2890159.4 | F10: =-Assumptions!F12* 'Income Statement'!F9 -> -2919061 | G10: =-Assumptions!G12* 'Income Statement'!G9 -> -2948251.6 | H10: =-Assumptions!H12* 'Income Statement'!H9 -> -2977734.2 | I10: =-Assumptions!I12* 'Income Statement'!I9 -> -3007511.5 | J10: =-Assumptions!J12* 'Income Statement'!J9 -> -3037586.6
B11: Gross profit | C11: =SUM(C9:C10) -> 442800 | D11: =SUM(D9:D10) -> 648700 | E11: =E9+E10 -> 550506.56 | F11: =F9+F10 -> 556011.63 | G11: =G9+G10 -> 561571.74 | H11: =H9+H10 -> 567187.46 | I11: =I9+I10 -> 572859.33 | J11: =J9+J10 -> 578587.93
B12: Margin | C12: =C11/C9 -> 0.12519792 | D12: =D11/D9 -> 0.19042447 | E12: =E11/E9 -> 0.16 | F12: =F11/F9 -> 0.16 | G12: =G11/G9 -> 0.16 | H12: =H11/H9 -> 0.16 | I12: =I11/I9 -> 0.16 | J12: =J11/J9 -> 0.16
B14: Administration | C14: -159100 | D14: -172500 | E14: =-Assumptions!E13*E9 -> -172033.3 | F14: =-Assumptions!F13*F9 -> -173753.63 | G14: =-Assumptions!G13*G9 -> -175491.17 | H14: =-Assumptions!H13*H9 -> -177246.08 | I14: =-Assumptions!I13*I9 -> -179018.54 | J14: =-Assumptions!J13*J9 -> -180808.73
B15: Other operating income pre OP | C15: 40700 | D15: 33700 | E15: =Assumptions!E14 -> 30000 | F15: =Assumptions!F14 -> 30000 | G15: =Assumptions!G14 -> 30000 | H15: =Assumptions!H14 -> 30000 | I15: =Assumptions!I14 -> 30000 | J15: =Assumptions!J14 -> 30000
B16: Exceptional items pre OP | C16: 0 | D16: 0 | E16: 0 | F16: 0 | G16: 0 | H16: 0 | I16: 0 | J16: 0
B17: EBITDA | C17: =C11+SUM(C14:C16) -> 324400 | D17: =D11+SUM(D14:D16) -> 509900 | E17: =E11+SUM(E14:E16) -> 408473.26 | F17: =F11+SUM(F14:F16) -> 412257.99 | G17: =G11+SUM(G14:G16) -> 416080.57 | H17: =H11+SUM(H14:H16) -> 419941.38 | I17: =I11+SUM(I14:I16) -> 423840.79 | J17: =J11+SUM(J14:J16) -> 427779.2
B18: Margin | C18: =C17/C9 -> 0.09172133 | D18: =D17/D9 -> 0.14968003 | E18: =E17/E9 -> 0.11871924 | F18: =F17/F9 -> 0.11863291 | G18: =G17/G9 -> 0.11854744 | H18: =H17/H9 -> 0.11846281 | I18: =I17/I9 -> 0.11837902 | J18: =J17/J9 -> 0.11829606
B20: Depreciation | C20: -6100 | D20: -6000 | E20: =--'Side calculations'!E11 -> -14566.109 | F20: ='Side calculations'!F11 -> -20740.747 | G20: ='Side calculations'!G11 -> -25298.742 | H20: ='Side calculations'!H11 -> -28722.45 | I20: ='Side calculations'!I11 -> -31351.64 | J20: ='Side calculations'!J11 -> -33425.674
B21: Amortisation and impairment | C21: 0 | D21: 0 | E21: =Assumptions!E17 -> 0 | F21: =Assumptions!F17 -> 0 | G21: =Assumptions!G17 -> 0 | H21: =Assumptions!H17 -> 0 | I21: =Assumptions!I17 -> 0 | J21: =Assumptions!J17 -> 0
B22: EBIT | C22: =C17+C20+C21 -> 318300 | D22: =D17+D20+D21 -> 503900 | E22: =E17+E20+E21 -> 397654.41 | F22: =F17+F20+F21 -> 399124.18 | G22: =G17+G20+G21 -> 402363.49 | H22: =H17+H20+H21 -> 406893.02 | I22: =I17+I20+I21 -> 412376.14 | J22: =J17+J20+J21 -> 418576.67
B23: Margin | C23: =C22/C9 -> 0.089996607 | D23: =D22/D9 -> 0.14791875 | E23: =E22/E9 -> 0.11444175 | F23: =F22/F9 -> 0.11261249 | G23: =G22/G9 -> 0.11130045 | H23: =H22/H9 -> 0.11034646 | I23: =I22/I9 -> 0.10964063 | J23: =J22/J9 -> 0.10910706
B25: Interest income | C25: 1600 | D25: 9900 | E25: =Assumptions!E18 *'Balance sheet'!E9 -> 16652.396 | F25: =Assumptions!F18 *'Balance sheet'!F9 -> 18568.136 | G25: =Assumptions!G18 *'Balance sheet'!G9 -> 20483.464 | H25: =Assumptions!H18 *'Balance sheet'!H9 -> 22514.954 | I25: =Assumptions!I18 *'Balance sheet'!I9 -> 24649.362 | J25: =Assumptions!J18 *'Balance sheet'!J9 -> 26877.837
B26: Interest expense | C26: -15700 | D26: -30800 | E26: =-'Side calculations'!E24-'Side calculations'!E30 -> -4936 | F26: =-'Side calculations'!F24-'Side calculations'!F30 -> -5434.75 | G26: =-'Side calculations'!G24-'Side calculations'!G30 -> -5128.5 | H26: =-'Side calculations'!H24-'Side calculations'!H30 -> -4728.5 | I26: =-'Side calculations'!I24-'Side calculations'!I30 -> -4328.5 | J26: =-'Side calculations'!J24-'Side calculations'!J30 -> -3928.5
B27: Profit before tax | C27: =C22+C25+C26 -> 304200 | D27: =D22+D25+D26 -> 483000 | E27: =E22+E25+E26 -> 409370.81 | F27: =F22+F25+F26 -> 412257.57 | G27: =G22+G25+G26 -> 417718.45 | H27: =H22+H25+H26 -> 424679.48 | I27: =I22+I25+I26 -> 432697 | J27: =J22+J25+J26 -> 441526
B29: Tax | C29: -61600 | D29: -118000 | E29: =+Assumptions!E19*'Income Statement'!E27*-1 -> -102342.7 | F29: =+Assumptions!F19*'Income Statement'!F27*-1 -> -103064.39 | G29: =+Assumptions!G19*'Income Statement'!G27*-1 -> -104429.61 | H29: =+Assumptions!H19*'Income Statement'!H27*-1 -> -106169.87 | I29: =+Assumptions!I19*'Income Statement'!I27*-1 -> -108174.25 | J29: =+Assumptions!J19*'Income Statement'!J27*-1 -> -110381.5
B30: Profit after tax | C30: =C27+C29 -> 242600 | D30: =D27+D29 -> 365000 | E30: =E27+E29 -> 307028.11 | F30: =F27+F29 -> 309193.18 | G30: =G27+G29 -> 313288.84 | H30: =H27+H29 -> 318509.61 | I30: =I27+I29 -> 324522.75 | J30: =J27+J29 -> 331144.5
B32: Extraordinary items | C32: 0 | D32: 0 | E32: 0 | F32: 0 | G32: 0 | H32: 0 | I32: 0 | J32: 0
B33: Net income | C33: =C30+C32 -> 242600 | D33: =D30+D32 -> 365000 | E33: =E30+E32 -> 307028.11 | F33: =F30+F32 -> 309193.18 | G33: =G30+G32 -> 313288.84 | H33: =H30+H32 -> 318509.61 | I33: =I30+I32 -> 324522.75 | J33: =J30+J32 -> 331144.5

Sheet Balance sheet
A1: =company&" Balance Sheet" -> BELLWAY P L C Balance Sheet
A2: ="in "&currency&" thousands" -> in GBP thousands
A5: Balance sheet
C7: =Assumptions!C10 -> 2022 | D7: =Assumptions!D10 -> 2023 | E7: =Assumptions!E10 -> 2024 | F7: =Assumptions!F10 -> 2025 | G7: =Assumptions!G10 -> 2026 | H7: =Assumptions!H10 -> 2027 | I7: =Assumptions!I10 -> 2028 | J7: =Assumptions!J10 -> 2029
B9: Cash and short term investments | C9: 375300 | D9: 362000 | E9: =-E33-SUM(E10:E12,E18) -> 555079.86 | F9: =-F33-SUM(F10:F12,F18) -> 618937.87 | G9: =-G33-SUM(G10:G12,G18) -> 682782.12 | H9: =-H33-SUM(H10:H12,H18) -> 750498.48 | I9: =-I33-SUM(I10:I12,I18) -> 821645.39 | J9: =-J33-SUM(J10:J12,J18) -> 895927.88
B10: Accounts receivable | C10: 47500 | D10: 34600 | E10: =Assumptions!E23*'Income Statement'!E9 -> 34406.66 | F10: =Assumptions!F23*'Income Statement'!F9 -> 34750.727 | G10: =Assumptions!G23*'Income Statement'!G9 -> 35098.234 | H10: =Assumptions!H23*'Income Statement'!H9 -> 35449.216 | I10: =Assumptions!I23*'Income Statement'!I9 -> 35803.708 | J10: =Assumptions!J23*'Income Statement'!J9 -> 36161.745
B11: Inventories | C11: 4423600 | D11: 4575600 | E11: =Assumptions!E24*'Income Statement'!E9 -> 4472865.8 | F11: =Assumptions!F24*'Income Statement'!F9 -> 4517594.5 | G11: =Assumptions!G24*'Income Statement'!G9 -> 4562770.4 | H11: =Assumptions!H24*'Income Statement'!H9 -> 4608398.1 | I11: =Assumptions!I24*'Income Statement'!I9 -> 4654482.1 | J11: =Assumptions!J24*'Income Statement'!J9 -> 4701026.9
B12: Other current assets | C12: 67100 | D12: 62500 | E12: =Assumptions!E25*'Income Statement'!E9 -> 61931.988 | F12: =Assumptions!F25*'Income Statement'!F9 -> 62551.308 | G12: =Assumptions!G25*'Income Statement'!G9 -> 63176.821 | H12: =Assumptions!H25*'Income Statement'!H9 -> 63808.589 | I12: =Assumptions!I25*'Income Statement'!I9 -> 64446.675 | J12: =Assumptions!J25*'Income Statement'!J9 -> 65091.142
B13: Total current assets | C13: =SUM(C9:C12) -> 4913500 | D13: =SUM(D9:D12) -> 5034700 | E13: =SUM(E9:E12) -> 5169524 | F13: =SUM(F9:F12) -> 5325670.8 | G13: =SUM(G9:G12) -> 5483649.8 | H13: =SUM(H9:H12) -> 5647383.5 | I13: =SUM(I9:I12) -> 5816468.1 | J13: =SUM(J9:J12) -> 5990647
B15: PP&E | C15: 13600 | D15: 14500 | E15: ='Side calculations'!E12 -> 34681.211 | F15: ='Side calculations'!F12 -> 49382.731 | G15: ='Side calculations'!G12 -> 60235.1 | H15: ='Side calculations'!H12 -> 68386.785 | I15: ='Side calculations'!I12 -> 74646.762 | J15: ='Side calculations'!J12 -> 79584.937
B16: Goodwill and intangible assets | C16: 37400 | D16: 47700 | E16: =Assumptions!E27 -> 47700 | F16: =Assumptions!F27 -> 47700 | G16: =Assumptions!G27 -> 47700 | H16: =Assumptions!H27 -> 47700 | I16: =Assumptions!I27 -> 47700 | J16: =Assumptions!J27 -> 47700
B17: Other long term assets | C17: 20600 | D17: 17200 | E17: =Assumptions!E28*'Income Statement'!E9 -> 17203.33 | F17: =Assumptions!F28*'Income Statement'!F9 -> 17375.363 | G17: =Assumptions!G28*'Income Statement'!G9 -> 17549.117 | H17: =Assumptions!H28*'Income Statement'!H9 -> 17724.608 | I17: =Assumptions!I28*'Income Statement'!I9 -> 17901.854 | J17: =Assumptions!J28*'Income Statement'!J9 -> 18080.873
B18: Total long term assets | C18: =SUM(C15:C17) -> 71600 | D18: =SUM(D15:D17) -> 79400 | E18: =SUM(E15:E17) -> 99754.871 | F18: =SUM(F15:F17) -> 114803.86 | G18: =SUM(G15:G17) -> 126010.66 | H18: =SUM(H15:H17) -> 134523.85 | I18: =SUM(I15:I17) -> 141152.57 | J18: =SUM(J15:J17) -> 146466.86
B19: Total assets | C19: =C13+C18 -> 4985100 | D19: =D13+D18 -> 5114100 | E19: =E13+E18 -> 5269278.8 | F19: =F13+F18 -> 5440474.7 | G19: =G13+G18 -> 5609660.4 | H19: =H13+H18 -> 5781907.3 | I19: =I13+I18 -> 5957620.7 | J19: =J13+J18 -> 6137113.9
B21: Short term debt | C21: -2900 | D21: -3100 | E21: =-'Side calculations'!E29 -> -2600 | F21: =-'Side calculations'!F29 -> -2100 | G21: =-'Side calculations'!G29 -> -2100 | H21: =-'Side calculations'!H29 -> -2100 | I21: =-'Side calculations'!I29 -> -2100 | J21: =-'Side calculations'!J29 -> -2100
B22: Accounts payable | C22: -585100 | D22: -579600 | E22: =-Assumptions!E30*'Income Statement'!E9 -> -584913.22 | F22: =-Assumptions!F30*'Income Statement'!F9 -> -590762.35 | G22: =-Assumptions!G30*'Income Statement'!G9 -> -596669.98 | H22: =-Assumptions!H30*'Income Statement'!H9 -> -602636.68 | I22: =-Assumptions!I30*'Income Statement'!I9 -> -608663.04 | J22: =-Assumptions!J30*'Income Statement'!J9 -> -614749.67
B23: Other current liabilities | C23: -383000 | D23: -422800 | E23: =-Assumptions!E31*'Income Statement'!E9 -> -412879.92 | F23: =-Assumptions!F31*'Income Statement'!F9 -> -417008.72 | G23: =-Assumptions!G31*'Income Statement'!G9 -> -421178.81 | H23: =-Assumptions!H31*'Income Statement'!H9 -> -425390.59 | I23: =-Assumptions!I31*'Income Statement'!I9 -> -429644.5 | J23: =-Assumptions!J31*'Income Statement'!J9 -> -433940.95
B24: Total current liabilities | C24: =SUM(C21:C23) -> -971000 | D24: =SUM(D21:D23) -> -1005500 | E24: =SUM(E21:E23) -> -1000393.1 | F24: =SUM(F21:F23) -> -1009871.1 | G24: =SUM(G21:G23) -> -1019948.8 | H24: =SUM(H21:H23) -> -1030127.3 | I24: =SUM(I21:I23) -> -1040407.5 | J24: =SUM(J21:J23) -> -1050790.6
B26: Long term debt | C26: -144300 | D26: -141900 | E26: =-'Side calculations'!E23 -> -136900 | F26: =-'Side calculations'!F23 -> -131900 | G26: =-'Side calculations'!G23 -> -121900 | H26: =-'Side calculations'!H23 -> -111900 | I26: =-'Side calculations'!I23 -> -101900 | J26: =-'Side calculations'!J23 -> -91900
B27: Other LT liabilities | C27: -92300 | D27: -95400 | E27: =-Assumptions!E32*'Income Statement'!E9 -> -96338.648 | F27: =-Assumptions!F32*'Income Statement'!F9 -> -97302.034 | G27: =-Assumptions!G32*'Income Statement'!G9 -> -98275.055 | H27: =-Assumptions!H32*'Income Statement'!H9 -> -99257.805 | I27: =-Assumptions!I32*'Income Statement'!I9 -> -100250.38 | J27: =-Assumptions!J32*'Income Statement'!J9 -> -101252.89
B28: Provisions for liabilities | C28: -409700 | D28: -409700 | E28: -409700 | F28: -409700 | G28: -409700 | H28: -409700 | I28: -409700 | J28: -409700
B29: Pension liabilities | C29: 0 | D29: 0 | E29: =Assumptions!E34 -> 0 | F29: =Assumptions!F34 -> 0 | G29: =Assumptions!G34 -> 0 | H29: =Assumptions!H34 -> 0 | I29: =Assumptions!I34 -> 0 | J29: =Assumptions!J34 -> 0
B30: Total long term liabilities | C30: =SUM(C26:C29) -> -646300 | D30: =SUM(D26:D29) -> -647000 | E30: =SUM(E26:E29) -> -642938.65 | F30: =SUM(F26:F29) -> -638902.03 | G30: =SUM(G26:G29) -> -629875.05 | H30: =SUM(H26:H29) -> -620857.81 | I30: =SUM(I26:I29) -> -611850.38 | J30: =SUM(J26:J29) -> -602852.89
B32: Shareholders' equity | C32: -3367800 | D32: -3461600 | E32: =-'Side calculations'!E18 -> -3615114.1 | F32: =-'Side calculations'!F18 -> -3769710.6 | G32: =-'Side calculations'!G18 -> -3926355.1 | H32: =-'Side calculations'!H18 -> -4085609.9 | I32: =-'Side calculations'!I18 -> -4247871.2 | J32: =-'Side calculations'!J18 -> -4413443.5
B33: Total L&E | C33: =C24+C30+C32 -> -4985100 | D33: =D24+D30+D32 -> -5114100 | E33: =E24+E30+E32 -> -5269278.8 | F33: =F24+F30+F32 -> -5440474.7 | G33: =G24+G30+G32 -> -5609660.4 | H33: =H24+H30+H32 -> -5781907.3 | I33: =I24+I30+I32 -> -5957620.7 | J33: =J24+J30+J32 -> -6137113.9
B34: Balance check | C34: =C19+C33 -> 0 | D34: =D19+D33 -> 0 | E34: =E19+E33 -> 0 | F34: =F19+F33 -> 0 | G34: =G19+G33 -> 0 | H34: =H19+H33 -> 0 | I34: =I19+I33 -> 0 | J34: =J19+J33 -> 0

Sheet DCF
A1: =company&" DCF analysis" -> BELLWAY P L C DCF analysis
A2: ="in "&currency&" thousands except per share data" -> in GBP thousands except per share data
E4: 1 | F4: =+E4+1 -> 2 | G4: =+F4+1 -> 3 | H4: =+G4+1 -> 4 | I4: =+H4+1 -> 5 | J4: =+I4+1 -> 6
E5: =Assumptions!E10 -> 2024 | F5: =Assumptions!F10 -> 2025 | G5: =Assumptions!G10 -> 2026 | H5: =Assumptions!H10 -> 2027 | I5: =Assumptions!I10 -> 2028 | J5: =Assumptions!J10 -> 2029
B7: EBIT | E7: ='Income Statement'!E22 -> 397654.41 | F7: ='Income Statement'!F22 -> 399124.18 | G7: ='Income Statement'!G22 -> 402363.49 | H7: ='Income Statement'!H22 -> 406893.02 | I7: ='Income Statement'!I22 -> 412376.14 | J7: ='Income Statement'!J22 -> 418576.67
B8: Tax on EBIT | E8: =-Assumptions!E19*DCF!E7 -> -99413.603 | F8: =-Assumptions!F19*DCF!F7 -> -99781.046 | G8: =-Assumptions!G19*DCF!G7 -> -100590.87 | H8: =-Assumptions!H19*DCF!H7 -> -101723.26 | I8: =-Assumptions!I19*DCF!I7 -> -103094.04 | J8: =-Assumptions!J19*DCF!J7 -> -104644.17
B9: NOPAT | E9: =SUM(E7:E8) -> 298240.81 | F9: =SUM(F7:F8) -> 299343.14 | G9: =SUM(G7:G8) -> 301772.62 | H9: =SUM(H7:H8) -> 305169.77 | I9: =SUM(I7:I8) -> 309282.11 | J9: =SUM(J7:J8) -> 313932.5
B11: +Depreciation | E11: =+'Income Statement'!E20*-1 -> 14566.109 | F11: =+'Income Statement'!F20*-1 -> 20740.747 | G11: =+'Income Statement'!G20*-1 -> 25298.742 | H11: =+'Income Statement'!H20*-1 -> 28722.45 | I11: =+'Income Statement'!I20*-1 -> 31351.64 | J11: =+'Income Statement'!J20*-1 -> 33425.674
B12: +Amortisation | E12: ='Income Statement'!E21 -> 0 | F12: ='Income Statement'!F21 -> 0 | G12: ='Income Statement'!G21 -> 0 | H12: ='Income Statement'!H21 -> 0 | I12: ='Income Statement'!I21 -> 0 | J12: ='Income Statement'!J21 -> 0
B13: -Capital expenditure | E13: =+'Side calculations'!E10*-1 -> -34406.66 | F13: =+'Side calculations'!F10*-1 -> -34750.727 | G13: =+'Side calculations'!G10*-1 -> -35098.234 | H13: =+'Side calculations'!H10*-1 -> -35449.216 | I13: =+'Side calculations'!I10*-1 -> -35803.708 | J13: =+'Side calculations'!J10*-1 -> -36161.745
B14: -Purchase of intangibles | E14: =-'Balance sheet'!E16*1 -> -47700 | F14: =-'Balance sheet'!F16*1 -> -47700 | G14: =-'Balance sheet'!G16*1 -> -47700 | H14: =-'Balance sheet'!H16*1 -> -47700 | I14: =-'Balance sheet'!I16*1 -> -47700 | J14: =-'Balance sheet'!J16*1 -> -47700
B15: -Increase in working capital | E15: =-'Side calculations'!D32+'Side calculations'!E32 -> -108102.41 | F15: =-'Side calculations'!E32+'Side calculations'!F32 -> 55669.976 | G15: =-'Side calculations'!F32+'Side calculations'!G32 -> 56226.676 | H15: =-'Side calculations'!G32+'Side calculations'!H32 -> 56788.942 | I15: =-'Side calculations'!H32+'Side calculations'!I32 -> 57356.832 | J15: =-'Side calculations'!I32+'Side calculations'!J32 -> 57930.4
B16: -Increase in other long term assets | E16: ='Balance sheet'!D17-'Balance sheet'!E17 -> -3.33 | F16: ='Balance sheet'!E17-'Balance sheet'!F17 -> -172.0333 | G16: ='Balance sheet'!F17-'Balance sheet'!G17 -> -173.75363 | H16: ='Balance sheet'!G17-'Balance sheet'!H17 -> -175.49117 | I16: ='Balance sheet'!H17-'Balance sheet'!I17 -> -177.24608 | J16: ='Balance sheet'!I17-'Balance sheet'!J17 -> -179.01854
B17: + Increase in LT liabilities excl debt | E17: =+('Balance sheet'!D30-'Balance sheet'!E30)-('Balance sheet'!D26-'Balance sheet'!E26) -> 938.648 | F17: =+('Balance sheet'!E30-'Balance sheet'!F30)-('Balance sheet'!E26-'Balance sheet'!F26) -> 963.38648 | G17: =+('Balance sheet'!F30-'Balance sheet'!G30)-('Balance sheet'!F26-'Balance sheet'!G26) -> 973.02034 | H17: =+('Balance sheet'!G30-'Balance sheet'!H30)-('Balance sheet'!G26-'Balance sheet'!H26) -> 982.75055 | I17: =+('Balance sheet'!H30-'Balance sheet'!I30)-('Balance sheet'!H26-'Balance sheet'!I26) -> 992.57805 | J17: =+('Balance sheet'!I30-'Balance sheet'!J30)-('Balance sheet'!I26-'Balance sheet'!J26) -> 1002.5038
B18: Free cash flow | E18: =+E9+SUM(E11:E17) -> 179094.81 | F18: =+F9+SUM(F11:F17) -> 350982.32 | G18: =+G9+SUM(G11:G17) -> 359541.76 | H18: =+H9+SUM(H11:H17) -> 367966.03 | I18: =+I9+SUM(I11:I17) -> 376343.04 | J18: =+J9+SUM(J11:J17) -> 384735.65
B21: WACC | C21: 0.08
B22: Long term growth rate | C22: 0.01
B24: Terminal value | J24: =+(J18*(1+g))/(WACC-g) -> 5551185.8
B26: Discount factor | E26: =1/(1+WACC)^E4 -> 0.92592593 | F26: =1/(1+WACC)^F4 -> 0.85733882 | G26: =1/(1+WACC)^G4 -> 0.79383224 | H26: =1/(1+WACC)^H4 -> 0.73502985 | I26: =1/(1+WACC)^I4 -> 0.6805832 | J26: =1/(1+WACC)^J4 -> 0.63016963
B27: PV of FCF | E27: =+E18*E26 -> 165828.53 | F27: =+F18*F26 -> 300910.77 | G27: =+G18*G26 -> 285415.84 | H27: =+H18*H26 -> 270466.02 | I27: =+I18*I26 -> 256132.75 | J27: =+J18*J26 -> 242448.72
B30: PV of FCF yr 1 - 6 | D30: =+SUM(E27:J27) -> 1521202.6
B31: PV of TV | D31: =+J24*J26 -> 3498188.7
B32: Enterprise value | D32: =D30+D31 -> 5019391.3
B33: -Debt | D33: =+'Balance sheet'!E21-'Balance sheet'!E26 -> 134300
B34: +Cash | D34: ='Balance sheet'!D9 -> 362000
B35: Equity value | D35: =+D32-D33+D34 -> 5247091.3
B36: Shares outstanding (th) | D36: 119450
B37: Implied price per share | D37: =+D35/D36 -> 43.927093
A40: Data table
B41: WACC variation | D41: 0.005
B42: G variation | D42: 0.005
D44: Growth rate
C45: =D37 -> 43.927093 | D45: =+E45-D42 -> 0.005 | E45: 0.01 | F45: =+E45+D42 -> 0.015
C46: =+C47+D41 -> 0.085 | D46: 43.927093 | E46: 43.927093 | F46: 43.927093
B47: WACC | C47: 0.08 | D47: 43.927093 | E47: 43.927093 | F47: 43.927093
C48: =+C47-D41 -> 0.075 | D48: 43.927093 | E48: 43.927093 | F48: 43.927093

Sheet Sensitivity
B2: Base case
E3: =LFY+1 -> 2024 | F3: =LFY+2 -> 2025 | G3: =LFY+3 -> 2026 | H3: =LFY+4 -> 2027 | I3: =LFY+5 -> 2028 | J3: =LFY+6 -> 2029
B4: Base case | E4: 0.02 | F4: 0.02 | G4: 0.02 | H4: 0.02 | I4: 0.02 | J4: 0.02
B5: Upside | E5: =E4+1% -> 0.03 | F5: =F4+1% -> 0.03 | G5: =G4+1% -> 0.03 | H5: =H4+1% -> 0.03 | I5: =I4+1% -> 0.03 | J5: =J4+1% -> 0.03
B6: Downside | E6: =E4-1% -> 0.01 | F6: =F4-1% -> 0.01 | G6: =G4-1% -> 0.01 | H6: =H4-1% -> 0.01 | I6: =I4-1% -> 0.01 | J6: =J4-1% -> 0.01
E8: =LFY+1 -> 2024 | F8: =LFY+2 -> 2025 | G8: =LFY+3 -> 2026 | H8: =LFY+4 -> 2027 | I8: =LFY+5 -> 2028 | J8: =LFY+6 -> 2029
B9: Sales growth | E9: =VLOOKUP($B$2,$B$4:$J$6,MATCH(E3,$E$8:$J$8)+3,FALSE) -> 0.02 | F9: =VLOOKUP($B$2,$B$4:$J$6,MATCH(F3,$E$8:$J$8)+3,FALSE) -> 0.02 | G9: =VLOOKUP($B$2,$B$4:$J$6,MATCH(G3,$E$8:$J$8)+3,FALSE) -> 0.02 | H9: =VLOOKUP($B$2,$B$4:$J$6,MATCH(H3,$E$8:$J$8)+3,FALSE) -> 0.02 | I9: =VLOOKUP($B$2,$B$4:$J$6,MATCH(I3,$E$8:$J$8)+3,FALSE) -> 0.02 | J9: =VLOOKUP($B$2,$B$4:$J$6,MATCH(J3,$E$8:$J$8)+3,FALSE) -> 0.02
